MANIFEST.in
README.md
requirements.txt
setup.cfg
setup.py
version
cli/gcs_to_table
cli/query_to_table
cli/table_to_gcs
gcloud_utils/__init__.py
gcloud_utils/base_client.py
gcloud_utils/compute.py
gcloud_utils/dataproc.py
gcloud_utils/functions.py
gcloud_utils/logger.py
gcloud_utils/ml_engine.py
gcloud_utils/storage.py
gcloud_utils.egg-info/PKG-INFO
gcloud_utils.egg-info/SOURCES.txt
gcloud_utils.egg-info/dependency_links.txt
gcloud_utils.egg-info/requires.txt
gcloud_utils.egg-info/top_level.txt
gcloud_utils/bigquery/__init__.py
gcloud_utils/bigquery/bigquery.py
gcloud_utils/bigquery/query_builder.py
tests/__init__.py
tests/test_base_client.py
tests/test_compute.py
tests/test_dataproc.py
tests/test_ml_engine.py
tests/test_ml_engine_start_training.py
tests/test_storage.py
tests/bigquery/__init__.py
tests/bigquery/test_bigquery.py
tests/bigquery/test_query_builder.py