Metadata-Version: 1.1
Name: gcloud-utils
Version: 2.20.5
Summary: handle gcloud services
Home-page: https://github.com/globocom/gcloud-utils/
Author: Big Data
Author-email: bigdata@corp.globo.com
License: MIT
Download-URL: https://github.com/globocom/gcloud-utils/archive/master.zip
Platform: UNKNOWN
